README.md
setup.py
cifl_auth_wrapper/__init__.py
cifl_auth_wrapper.egg-info/PKG-INFO
cifl_auth_wrapper.egg-info/SOURCES.txt
cifl_auth_wrapper.egg-info/dependency_links.txt
cifl_auth_wrapper.egg-info/not-zip-safe
cifl_auth_wrapper.egg-info/requires.txt
cifl_auth_wrapper.egg-info/top_level.txt
cifl_auth_wrapper/cifl_auth/__init__.py