Metadata-Version: 1.0
Name: cifl-auth-wrapper
Version: 0.1.5
Summary: A wrapper for CIFL taps and targets
Home-page: https://github.com/coding-is-for-losers/singer-taps-and-targets-v1.1/tree/master/cifl_google_wrapper
Author: CIFL
Author-email: UNKNOWN
License: MIT
Platform: UNKNOWN
